LICENSE
README.rst
setup.py
maxsmooth/DCF.py
maxsmooth/Data_save.py
maxsmooth/Models.py
maxsmooth/__init__.py
maxsmooth/best_basis.py
maxsmooth/chidist_plotter.py
maxsmooth/derivatives.py
maxsmooth/parameter_plotter.py
maxsmooth/qp.py
maxsmooth.egg-info/PKG-INFO
maxsmooth.egg-info/SOURCES.txt
maxsmooth.egg-info/dependency_links.txt
maxsmooth.egg-info/requires.txt
maxsmooth.egg-info/top_level.txt