Metadata-Version: 2.1
Name: maxsmooth
Version: 1.2.1
Summary: maxsmooth:Derivative Constrained Function Fitting
Home-page: https://github.com/htjb/maxsmooth
Author: Harry T. J. Bevins
Author-email: htjb2@cam.ac.uk
License: MIT
Platform: UNKNOWN
Classifier: Intended Audience :: Science/Research
Classifier: Natural Language :: English
Classifier: License :: OSI Approved :: MIT License
Classifier: Programming Language :: Python :: 3.6
Classifier: Programming Language :: Python :: 3.7
Classifier: Programming Language :: Python :: 3.8
Classifier: Topic :: Scientific/Engineering
Classifier: Topic :: Scientific/Engineering :: Astronomy
Classifier: Topic :: Scientific/Engineering :: Physics
Provides-Extra: docs
License-File: LICENSE
